congress_tempest_plugin/__init__.py
congress_tempest_plugin/config.py
congress_tempest_plugin/plugin.py
congress_tempest_plugin/services/__init__.py
congress_tempest_plugin/services/congress_network/__init__.py
congress_tempest_plugin/services/congress_network/qos_client.py
congress_tempest_plugin/services/congress_network/qos_rule_client.py
congress_tempest_plugin/services/policy/__init__.py
congress_tempest_plugin/services/policy/policy_client.py
congress_tempest_plugin/tests/__init__.py
congress_tempest_plugin/tests/api/__init__.py
congress_tempest_plugin/tests/scenario/__init__.py
congress_tempest_plugin/tests/scenario/helper.py
congress_tempest_plugin/tests/scenario/manager.py
congress_tempest_plugin/tests/scenario/manager_congress.py
congress_tempest_plugin/tests/scenario/test_congress_basic_ops.py
congress_tempest_plugin/tests/scenario/test_congress_z3.py
congress_tempest_plugin/tests/scenario/congress_datasources/__init__.py
congress_tempest_plugin/tests/scenario/congress_datasources/_test_keystonev2.py
congress_tempest_plugin/tests/scenario/congress_datasources/test_aodh.py
congress_tempest_plugin/tests/scenario/congress_datasources/test_cfg_validator.py
congress_tempest_plugin/tests/scenario/congress_datasources/test_cinder.py
congress_tempest_plugin/tests/scenario/congress_datasources/test_doctor.py
congress_tempest_plugin/tests/scenario/congress_datasources/test_glancev2.py
congress_tempest_plugin/tests/scenario/congress_datasources/test_heat.py
congress_tempest_plugin/tests/scenario/congress_datasources/test_ironic.py
congress_tempest_plugin/tests/scenario/congress_datasources/test_keystonev3.py
congress_tempest_plugin/tests/scenario/congress_datasources/test_mistral.py
congress_tempest_plugin/tests/scenario/congress_datasources/test_monasca.py
congress_tempest_plugin/tests/scenario/congress_datasources/test_murano.py
congress_tempest_plugin/tests/scenario/congress_datasources/test_neutronv2.py
congress_tempest_plugin-1.0.0.dist-info/AUTHORS
congress_tempest_plugin-1.0.0.dist-info/LICENSE
congress_tempest_plugin-1.0.0.dist-info/METADATA
congress_tempest_plugin-1.0.0.dist-info/WHEEL
congress_tempest_plugin-1.0.0.dist-info/entry_points.txt
congress_tempest_plugin-1.0.0.dist-info/pbr.json
congress_tempest_plugin-1.0.0.dist-info/top_level.txt
congress_tempest_plugin-1.0.0.dist-info/RECORD
